miotp/__init__.py
miotp/__version__.py
miotp/main.py
miotp/otp.py
miotp/totp.py
miotp-1.0.4.data/scripts/cool
miotp-1.0.4.dist-info/METADATA
miotp-1.0.4.dist-info/WHEEL
miotp-1.0.4.dist-info/entry_points.txt
miotp-1.0.4.dist-info/top_level.txt
miotp-1.0.4.dist-info/RECORD
