Metadata-Version: 2.1
Name: miotp
Version: 1.0.4
Summary: miotp.
Home-page: https://minhht.com
Author: MinhHT
Author-email: htm.dev304@gmail.com
License: UNKNOWN
Platform: UNKNOWN
